{
  "schemaVersion": 1,
  "featureId": "feat_library_8ff47ca9e6",
  "title": "Node source ui-dashboard/src/app/bridge-flows",
  "summary": "Node/TypeScript source group ui-dashboard/src/app/bridge-flows with 7 files.",
  "kind": "library",
  "source": "node-source-group",
  "confidence": "medium",
  "entrypoints": [
    {
      "path": "ui-dashboard/package.json",
      "symbol": "ui-dashboard/src/app/bridge-flows",
      "route": null,
      "command": null
    }
  ],
  "ownedFiles": [
    {
      "path": "ui-dashboard/src/app/bridge-flows/_components/bridge-flows-page-client.tsx",
      "reason": "source group ui-dashboard/src/app/bridge-flows"
    },
    {
      "path": "ui-dashboard/src/app/bridge-flows/_components/bridge-overview-section.tsx",
      "reason": "source group ui-dashboard/src/app/bridge-flows"
    },
    {
      "path": "ui-dashboard/src/app/bridge-flows/_components/route-delivery-tile.tsx",
      "reason": "source group ui-dashboard/src/app/bridge-flows"
    },
    {
      "path": "ui-dashboard/src/app/bridge-flows/_components/transfer-row-cells.tsx",
      "reason": "source group ui-dashboard/src/app/bridge-flows"
    },
    {
      "path": "ui-dashboard/src/app/bridge-flows/_components/transfers-table.tsx",
      "reason": "source group ui-dashboard/src/app/bridge-flows"
    },
    {
      "path": "ui-dashboard/src/app/bridge-flows/opengraph-image.tsx",
      "reason": "source group ui-dashboard/src/app/bridge-flows"
    },
    {
      "path": "ui-dashboard/src/app/bridge-flows/page.tsx",
      "reason": "source group ui-dashboard/src/app/bridge-flows"
    }
  ],
  "contextFiles": [
    {
      "path": "ui-dashboard/package.json",
      "reason": "package manifest"
    },
    {
      "path": "ui-dashboard/src/app/__tests__/page.test.tsx",
      "reason": "associated test"
    },
    {
      "path": "ui-dashboard/src/app/address-book/[address]/__tests__/page.test.tsx",
      "reason": "associated test"
    },
    {
      "path": "ui-dashboard/src/app/address-book/__tests__/page.test.tsx",
      "reason": "associated test"
    },
    {
      "path": "ui-dashboard/src/app/bridge-flows/__tests__/page.test.tsx",
      "reason": "associated test"
    },
    {
      "path": "ui-dashboard/src/app/pool/[poolId]/__tests__/page.test.tsx",
      "reason": "associated test"
    },
    {
      "path": "ui-dashboard/src/app/pool/[poolId]/page.test.tsx",
      "reason": "associated test"
    },
    {
      "path": "ui-dashboard/src/app/pools/__tests__/page.test.tsx",
      "reason": "associated test"
    }
  ],
  "tests": [
    {
      "path": "ui-dashboard/src/app/__tests__/page.test.tsx",
      "command": "pnpm --dir ui-dashboard test"
    },
    {
      "path": "ui-dashboard/src/app/address-book/[address]/__tests__/page.test.tsx",
      "command": "pnpm --dir ui-dashboard test"
    },
    {
      "path": "ui-dashboard/src/app/address-book/__tests__/page.test.tsx",
      "command": "pnpm --dir ui-dashboard test"
    },
    {
      "path": "ui-dashboard/src/app/bridge-flows/__tests__/page.test.tsx",
      "command": "pnpm --dir ui-dashboard test"
    },
    {
      "path": "ui-dashboard/src/app/pool/[poolId]/__tests__/page.test.tsx",
      "command": "pnpm --dir ui-dashboard test"
    },
    {
      "path": "ui-dashboard/src/app/pool/[poolId]/page.test.tsx",
      "command": "pnpm --dir ui-dashboard test"
    },
    {
      "path": "ui-dashboard/src/app/pools/__tests__/page.test.tsx",
      "command": "pnpm --dir ui-dashboard test"
    }
  ],
  "tags": [
    "node",
    "typescript",
    "source-group",
    "project:@mento-protocol/ui-dashboard",
    "project-root:ui-dashboard"
  ],
  "trustBoundaries": [],
  "status": "fixed",
  "lock": null,
  "findingIds": [
    "fnd_sig-feat-library-8ff47ca9e6-b9eb_bd0ff44475"
  ],
  "patchAttemptIds": [],
  "analysisHistory": [
    {
      "runId": "20260520T092843-0eb58e",
      "kind": "review",
      "summary": "1 finding(s)",
      "provider": "codex",
      "model": null,
      "createdAt": "2026-05-20T09:31:07.550Z"
    }
  ],
  "createdAt": "2026-05-17T11:26:44.015Z",
  "updatedAt": "2026-05-20T09:43:51.691Z"
}
